AUTHORS.md
LICENSE.md
MANIFEST.in
README.md
setup.py
bce/__init__.py
bce/option.py
bce.egg-info/PKG-INFO
bce.egg-info/SOURCES.txt
bce.egg-info/dependency_links.txt
bce.egg-info/entry_points.txt
bce.egg-info/requires.txt
bce.egg-info/top_level.txt
bce/base/__init__.py
bce/base/stack.py
bce/base/version.py
bce/database/__init__.py
bce/database/bundled/__init__.py
bce/database/bundled/abbreviation.py
bce/dom/__init__.py
bce/dom/mathml/__init__.py
bce/dom/mathml/all.py
bce/dom/mathml/base.py
bce/dom/mathml/fraction.py
bce/dom/mathml/number.py
bce/dom/mathml/operator.py
bce/dom/mathml/root.py
bce/dom/mathml/row.py
bce/dom/mathml/sqrt.py
bce/dom/mathml/sub.py
bce/dom/mathml/sub_sup.py
bce/dom/mathml/sup.py
bce/dom/mathml/text.py
bce/dom/mathml/types.py
bce/locale/__init__.py
bce/locale/initializer.py
bce/locale/option.py
bce/locale/registry.py
bce/locale/tree.py
bce/logic/__init__.py
bce/logic/balancer/__init__.py
bce/logic/balancer/direction.py
bce/logic/balancer/error.py
bce/logic/balancer/initializer.py
bce/logic/balancer/l10n.py
bce/logic/balancer/main.py
bce/logic/balancer/merger.py
bce/logic/balancer/model.py
bce/logic/balancer/option.py
bce/logic/common/__init__.py
bce/logic/common/error.py
bce/logic/common/initializer.py
bce/logic/common/l10n.py
bce/math/__init__.py
bce/math/constant.py
bce/math/equation.py
bce/math/matrix.py
bce/parser/__init__.py
bce/parser/ast/__init__.py
bce/parser/ast/base.py
bce/parser/ast/molecule.py
bce/parser/cexp/__init__.py
bce/parser/cexp/error.py
bce/parser/cexp/implementation.py
bce/parser/cexp/initializer.py
bce/parser/cexp/l10n.py
bce/parser/cexp/parser.py
bce/parser/cexp/printer_mathml.py
bce/parser/cexp/printer_text.py
bce/parser/cexp/substitution.py
bce/parser/cexp/token.py
bce/parser/common/__init__.py
bce/parser/common/error.py
bce/parser/common/initializer.py
bce/parser/common/l10n.py
bce/parser/common/token.py
bce/parser/interface/__init__.py
bce/parser/interface/cexp_parser.py
bce/parser/interface/mexp_parser.py
bce/parser/interface/molecule_parser.py
bce/parser/interface/option.py
bce/parser/interface/printer.py
bce/parser/mexp/__init__.py
bce/parser/mexp/error.py
