Metadata-Version: 1.1
Name: bce
Version: 4.7.9647
Summary: A chemical equation balancer.
Home-page: https://bce.xiaojsoft.org/
Author: The BCE Authors
Author-email: taiki_akita@163.com
License: BSD
Keywords: bce,chemistry,chemical,equation
Platform: UNKNOWN
Classifier: Development Status :: 5 - Production/Stable
Classifier: License :: OSI Approved :: BSD License
Classifier: Natural Language :: Chinese (Simplified)
Classifier: Natural Language :: English
Classifier: Operating System :: OS Independent
Classifier: Programming Language :: Python
Classifier: Topic :: Scientific/Engineering :: Chemistry
